MathLang/__init__.py
MathLang/Core/__init__.py
MathLang/Core/adaptors.py
MathLang/Core/compiler.py
MathLang/Core/lexer.py
MathLang/Core/nodes.py
MathLang/Core/parser.py
MathLang/Core/serialiser.py
MathLang_Core-2021.0.dist-info/LICENSE
MathLang_Core-2021.0.dist-info/METADATA
MathLang_Core-2021.0.dist-info/WHEEL
MathLang_Core-2021.0.dist-info/top_level.txt
MathLang_Core-2021.0.dist-info/RECORD
